gantt_lib/__init__.py
gantt_lib/gantt_main.py
gantt_lib_lautarodapin-0.0.5.dist-info/LICENSE
gantt_lib_lautarodapin-0.0.5.dist-info/METADATA
gantt_lib_lautarodapin-0.0.5.dist-info/WHEEL
gantt_lib_lautarodapin-0.0.5.dist-info/top_level.txt
gantt_lib_lautarodapin-0.0.5.dist-info/RECORD
