Metadata-Version: 2.1
Name: gantt-lib-lautarodapin
Version: 0.0.5
Summary: Extension of `python-gantt` with added functionality for django
Home-page: https://github.com/lautarodapin/gantt-lib
Author: Dapino Lautaro
Author-email: lautarodapin@gmail.com
License: UNKNOWN
Platform: UNKNOWN
Classifier: Programming Language :: Python :: 3
Classifier: Programming Language :: Python :: 3.7
Classifier: Programming Language :: Python :: 3.8
Classifier: Development Status :: 3 - Alpha
Requires-Python: >=3.7
Requires-Dist: python-gantt (~=0.6.0)
